PyEasing/__init__.py
PyEasing/easing.py
pyeasing-0.1.dist-info/LICENSE
pyeasing-0.1.dist-info/METADATA
pyeasing-0.1.dist-info/WHEEL
pyeasing-0.1.dist-info/top_level.txt
pyeasing-0.1.dist-info/RECORD
